{
  "goodsItemInfo":[
    {
      "goodPic":"../images/gooditem2.jpg",
      "goodTitle":"宝宝新鲜水果(最新鲜的水果，宝宝吃了健康成长)",
      "goodPrice":"59.00",
      "id":0
    },
    {
      "goodPic":"../images/gooditem2.jpg",
      "goodTitle":"宝宝月指黄瓜(馈赠佳品)",
      "goodPrice":"119.00",
      "id":1
    },
    {
      "goodPic":"../images/gooditem2.jpg",
      "goodTitle":"宝宝鲜蔬面(健康美食，健康生活)",
      "goodPrice":"205.00",
      "id":2
    },
    {
      "goodPic":"../images/gooditem2.jpg",
      "goodTitle":"宝宝鲜蔬面",
      "goodPrice":"789.00",
      "id":3
    },
    {
      "goodPic":"../images/gooditem2.jpg",
      "goodTitle":"宝宝鲜蔬面",
      "goodPrice":"205.00",
      "id":2
    },
    {
      "goodPic":"../images/gooditem2.jpg",
      "goodTitle":"宝宝鲜蔬面",
      "goodPrice":"789.00",
      "id":3
    },
    {
      "goodPic":"../images/gooditem2.jpg",
      "goodTitle":"宝宝鲜蔬面",
      "goodPrice":"789.00",
      "id":3
    },
    {
      "goodPic":"../images/gooditem2.jpg",
      "goodTitle":"宝宝鲜蔬面",
      "goodPrice":"205.00",
      "id":2
    },
    {
      "goodPic":"../images/gooditem2.jpg",
      "goodTitle":"宝宝鲜蔬面",
      "goodPrice":"789.00",
      "id":3
    },
    {
      "goodPic":"../images/gooditem2.jpg",
      "goodTitle":"宝宝鲜蔬面",
      "goodPrice":"789.00",
      "id":3
    },
    {
      "goodPic":"../images/gooditem2.jpg",
      "goodTitle":"宝宝鲜蔬面",
      "goodPrice":"205.00",
      "id":2
    },
    {
      "goodPic":"../images/gooditem2.jpg",
      "goodTitle":"宝宝鲜蔬面",
      "goodPrice":"789.00",
      "id":3
    },
    {
      "goodPic":"../images/gooditem2.jpg",
      "goodTitle":"宝宝鲜蔬面",
      "goodPrice":"789.00",
      "id":3
    },
    {
      "goodPic":"../images/gooditem2.jpg",
      "goodTitle":"宝宝鲜蔬面",
      "goodPrice":"205.00",
      "id":2
    },
    {
      "goodPic":"../images/gooditem.jpg",
      "goodTitle":"宝宝鲜蔬面",
      "goodPrice":"789.00",
      "id":3
    },
    {
      "goodPic":"../images/gooditem.jpg",
      "goodTitle":"宝宝鲜蔬面",
      "goodPrice":"789.00",
      "id":3
    },
    {
      "goodPic":"../images/gooditem.jpg",
      "goodTitle":"宝宝鲜蔬面",
      "goodPrice":"205.00",
      "id":2
    },
    {
      "goodPic":"../images/gooditem.jpg",
      "goodTitle":"宝宝鲜蔬面",
      "goodPrice":"789.00",
      "id":3
    },
    {
      "goodPic":"../images/gooditem.jpg",
      "goodTitle":"宝宝鲜蔬面",
      "goodPrice":"789.00",
      "id":3
    },
    {
      "goodPic":"../images/gooditem.jpg",
      "goodTitle":"宝宝鲜蔬面",
      "goodPrice":"205.00",
      "id":2
    },
    {
      "goodPic":"../images/gooditem.jpg",
      "goodTitle":"宝宝鲜蔬面",
      "goodPrice":"789.00",
      "id":3
    }
  ]
}
